setup.py
bqfoobar/__init__.py
bqfoobar.egg-info/PKG-INFO
bqfoobar.egg-info/SOURCES.txt
bqfoobar.egg-info/dependency_links.txt
bqfoobar.egg-info/not-zip-safe
bqfoobar.egg-info/top_level.txt