Metadata-Version: 1.0
Name: bqfoobar
Version: 0.1
Summary: The bqfoobar joke in the world
Home-page: http://github.com/BensonQiu/bqfoobar
Author: Flying Circus
Author-email: flyingcircus@example.com
License: MIT
Platform: UNKNOWN
